tink_finance/__init__.py
tink_finance/callback.py
tink_finance/client.py
tink_finance/exceptions.py
tink_finance/models.py
tink_finance/py.typed
tink_finance-0.1.0a1.dist-info/METADATA
tink_finance-0.1.0a1.dist-info/WHEEL
tink_finance-0.1.0a1.dist-info/licenses/LICENSE
tink_finance-0.1.0a1.dist-info/RECORD
