Metadata-Version: 2.4
Name: tink-finance
Version: 0.1.0a1
Summary: A Python client for the Tink Finance API
Project-URL: Homepage, https://github.com/ImpossiblyAI/tink-finance
Project-URL: Repository, https://github.com/ImpossiblyAI/tink-finance
Project-URL: Issues, https://github.com/ImpossiblyAI/tink-finance/issues
Author-email: Lawrence Ibarria <lawrence@impossibly.ai>
License: MIT License
License-File: LICENSE
Classifier: Development Status :: 3 - Alpha
Classifier: Intended Audience :: Developers
Classifier: License :: OSI Approved :: MIT License
Classifier: Operating System :: OS Independent
Classifier: Programming Language :: Python :: 3
Classifier: Programming Language :: Python :: 3.10
Classifier: Programming Language :: Python :: 3.11
Classifier: Programming Language :: Python :: 3.12
Classifier: Typing :: Typed
Requires-Python: >=3.10
Requires-Dist: httpx>=0.24.0
Requires-Dist: pydantic>=2.0.0
Requires-Dist: python-dotenv>=1.0.0
Provides-Extra: dev
Requires-Dist: black; extra == 'dev'
Requires-Dist: isort; extra == 'dev'
Requires-Dist: mypy; extra == 'dev'
